lumu_mcp_server/__init__.py
lumu_mcp_server/lumu_client.py
lumu_mcp_server/server.py
lumu_mcp_server/server_handlers.py
lumu_mcp_server-1.0.0.dist-info/METADATA
lumu_mcp_server-1.0.0.dist-info/WHEEL
lumu_mcp_server-1.0.0.dist-info/entry_points.txt
lumu_mcp_server-1.0.0.dist-info/licenses/LICENSE
lumu_mcp_server-1.0.0.dist-info/RECORD
