Metadata-Version: 2.4
Name: lumu-mcp-server
Version: 1.0.0
Summary: MCP server for Lumu Defender API integration with Claude Desktop
Project-URL: Homepage, https://github.com/jpyoda/lumu-mcp
Project-URL: Repository, https://github.com/jpyoda/lumu-mcp
Project-URL: Documentation, https://github.com/jpyoda/lumu-mcp#readme
Project-URL: Bug Tracker, https://github.com/jpyoda/lumu-mcp/issues
Author-email: Juan Pablo Gonzalez <your-email@example.com>
License: MIT
License-File: LICENSE
Keywords: ai,claude,cybersecurity,lumu,mcp,security
Classifier: Development Status :: 4 - Beta
Classifier: Intended Audience :: Developers
Classifier: Intended Audience :: Information Technology
Classifier: License :: OSI Approved :: MIT License
Classifier: Programming Language :: Python :: 3
Classifier: Programming Language :: Python :: 3.10
Classifier: Programming Language :: Python :: 3.11
Classifier: Programming Language :: Python :: 3.12
Classifier: Topic :: Security
Classifier: Topic :: Software Development :: Libraries :: Python Modules
Requires-Python: >=3.10
Requires-Dist: httpx>=0.27.0
Requires-Dist: mcp>=1.0.0
